byb2lsl/__init__.py
byb2lsl/driver.py
byb2lsl-0.0.6.dist-info/LICENSE.txt
byb2lsl-0.0.6.dist-info/METADATA
byb2lsl-0.0.6.dist-info/WHEEL
byb2lsl-0.0.6.dist-info/top_level.txt
byb2lsl-0.0.6.dist-info/RECORD
