Metadata-Version: 2.1
Name: byb2lsl
Version: 0.0.6
Summary: A driver to connect the Heart&Brain kit from Backyard Brain to the LabStreamingLayer.
Home-page: https://github.com/yop0/BackyardBrainHeartBrain-LSL
Author: Johan Medrano
Author-email: johan.medrano@umontpellier.fr
License: UNKNOWN
Platform: UNKNOWN
Classifier: Programming Language :: Python :: 3
Classifier: License :: OSI Approved :: MIT License
Classifier: Operating System :: OS Independent
Requires-Python: >=2.7
Requires-Dist: pylsl
Requires-Dist: pyserial
Requires-Dist: numpy
